winmagic/__init__.py
winmagic/nscaife/COPYING.file
winmagic/nscaife/COPYING.libgnurx
winmagic/nscaife/libgnurx-0.dll
winmagic/nscaife/magic.mgc
winmagic/nscaife/magic1.dll
python_magic_win64_0.4.15_fork-0.4.15.dist-info/LICENSE.md
python_magic_win64_0.4.15_fork-0.4.15.dist-info/METADATA
python_magic_win64_0.4.15_fork-0.4.15.dist-info/WHEEL
python_magic_win64_0.4.15_fork-0.4.15.dist-info/top_level.txt
python_magic_win64_0.4.15_fork-0.4.15.dist-info/RECORD
